monkeylearn/__init__.py
monkeylearn/base.py
monkeylearn/classification.py
monkeylearn/exceptions.py
monkeylearn/extraction.py
monkeylearn/response.py
monkeylearn/settings.py
monkeylearn/validation.py
monkeylearn/workflows.py
monkeylearn-3.6.0.dist-info/LICENSE.txt
monkeylearn-3.6.0.dist-info/METADATA
monkeylearn-3.6.0.dist-info/WHEEL
monkeylearn-3.6.0.dist-info/top_level.txt
monkeylearn-3.6.0.dist-info/RECORD
