Metadata-Version: 2.1
Name: monkeylearn
Version: 3.6.0
Summary: Official Python client for the MonkeyLearn API
Home-page: https://github.com/monkeylearn/monkeylearn-python
Author: MonkeyLearn
Author-email: hello@monkeylearn.com
License: UNKNOWN
Download-URL: https://github.com/monkeylearn/monkeylearn-python/tarball/v3.2.4
Keywords: monkeylearn,machine learning,python
Platform: UNKNOWN
Classifier: Development Status :: 5 - Production/Stable
Classifier: Programming Language :: Python :: 2
Classifier: Programming Language :: Python :: 3
Classifier: License :: OSI Approved :: MIT License
